hetzner_cloud_exporter/__init__.py
hetzner_cloud_exporter-0.1.0.dev5.dist-info/LICENSE
hetzner_cloud_exporter-0.1.0.dev5.dist-info/METADATA
hetzner_cloud_exporter-0.1.0.dev5.dist-info/WHEEL
hetzner_cloud_exporter-0.1.0.dev5.dist-info/entry_points.txt
hetzner_cloud_exporter-0.1.0.dev5.dist-info/top_level.txt
hetzner_cloud_exporter-0.1.0.dev5.dist-info/RECORD
