Metadata-Version: 2.1
Name: hetzner-cloud-exporter
Version: 0.1.0.dev5
Summary: Export hetzner cloud data
Home-page: https://github.com/adesso-mobile/hetzner_cloud_exporter
Author: adesso mobile solutions GmbH
Author-email: it-operations@adesso-mobile.de
License: UNKNOWN
Project-URL: Bug Tracker, https://github.com/adesso-mobile/hetzner_cloud_exporter/issues
Platform: UNKNOWN
Classifier: Programming Language :: Python :: 3
Classifier: License :: OSI Approved :: MIT License
Classifier: Operating System :: OS Independent
Requires-Python: >=3.6
Requires-Dist: requests
Requires-Dist: prometheus-client
